{"cameraMode":{"drawMode":0,"name":"Shaded","section":"Shading Mode"},"sceneLighting":true,"audioPlay":false,"sceneViewState":{"m_AlwaysRefresh":false,"showFog":true,"showSkybox":true,"showFlares":true,"showImageEffects":true,"showParticleSystems":true,"showVisualEffectGraphs":true,"m_FxEnabled":true},"in2DMode":false,"pivot":{"x":37.42753982543945,"y":26.524267196655275,"z":19.311511993408204},"rotation":{"x":-0.21156875789165498,"y":0.7096701860427856,"z":-0.23905673623085023,"w":-0.6281044483184815},"size":10.0,"orthographic":false}