{"cameraMode":{"drawMode":0,"name":"Shaded","section":"Shading Mode"},"sceneLighting":false,"audioPlay":false,"sceneViewState":{"m_AlwaysRefresh":false,"showFog":true,"showSkybox":false,"showFlares":true,"showImageEffects":true,"showParticleSystems":true,"showVisualEffectGraphs":true,"m_FxEnabled":true},"in2DMode":false,"pivot":{"x":0.0,"y":0.20389656722545625,"z":0.0},"rotation":{"x":-0.015731874853372575,"y":0.9813067317008972,"z":-0.09123726189136505,"w":-0.1691514402627945},"size":0.24976283311843873,"orthographic":false}